README.md
setup.py
daisy/__init__.py
daisy/config.py
daisy/formatted_target.py
daisy/task.py
luigi_daisy.egg-info/PKG-INFO
luigi_daisy.egg-info/SOURCES.txt
luigi_daisy.egg-info/dependency_links.txt
luigi_daisy.egg-info/entry_points.txt
luigi_daisy.egg-info/requires.txt
luigi_daisy.egg-info/top_level.txt